harmony/harmony.py
harmony/functions/core.py
harmony/functions/database.py
harmony/functions/lyrics.py
harmony/functions/playlist_manager.py
harmony/functions/queue_manager.py
harmony/integrations/lastfm.py
harmony/integrations/spotify.py
harmony/utils/core_utils.py
harmony/utils/track_utils.py
harmony/utils/url_parser.py
harmony_music-0.7.0.dist-info/METADATA
harmony_music-0.7.0.dist-info/WHEEL
harmony_music-0.7.0.dist-info/entry_points.txt
harmony_music-0.7.0.dist-info/licenses/LICENSE
harmony_music-0.7.0.dist-info/RECORD
