Metadata-Version: 2.4
Name: harmony-music
Version: 0.7.0
Summary: An open souce music streamer based on MPV.
Project-URL: Homepage, https://github.com/ZingyTomato/Harmony-Music
Project-URL: Repository, https://github.com/ZingyTomato/Harmony-Music
Project-URL: Issues, https://github.com/ZingyTomato/Harmony-Music/issues
Author: ZingyTomato
License:                     GNU GENERAL PUBLIC LICENSE
License-File: LICENSE
Keywords: cli-music,mpv,music,streaming
Classifier: Development Status :: 4 - Beta
Classifier: Environment :: Console
Classifier: Intended Audience :: End Users/Desktop
Classifier: License :: OSI Approved :: GNU General Public License v3 or later (GPLv3+)
Classifier: Operating System :: OS Independent
Classifier: Programming Language :: Python :: 3
Classifier: Programming Language :: Python :: 3.8
Classifier: Programming Language :: Python :: 3.9
Classifier: Programming Language :: Python :: 3.10
Classifier: Programming Language :: Python :: 3.11
Classifier: Programming Language :: Python :: 3.12
Classifier: Topic :: Internet :: WWW/HTTP :: Dynamic Content
Classifier: Topic :: Multimedia :: Sound/Audio
Classifier: Topic :: Utilities
Requires-Python: >=3.7
Requires-Dist: pylast
Requires-Dist: requests
Requires-Dist: rich
Requires-Dist: spotipy
Requires-Dist: syncedlyrics
